errorhandler/__init__.py
errorhandler/tests.py
errorhandler/version.txt
errorhandler-2.0.1.dist-info/DESCRIPTION.rst
errorhandler-2.0.1.dist-info/METADATA
errorhandler-2.0.1.dist-info/RECORD
errorhandler-2.0.1.dist-info/WHEEL
errorhandler-2.0.1.dist-info/metadata.json
errorhandler-2.0.1.dist-info/top_level.txt
